sparkle/__about__.py
sparkle/__init__.py
sparkle/CLI/__init__.py
sparkle/CLI/_cli_.py
sparkle/CLI/about.py
sparkle/CLI/add_feature_extractor.py
sparkle/CLI/add_instances.py
sparkle/CLI/add_solver.py
sparkle/CLI/check.py
sparkle/CLI/cleanup.py
sparkle/CLI/compute_features.py
sparkle/CLI/configure_solver.py
sparkle/CLI/construct_portfolio_selector.py
sparkle/CLI/generate_report.py
sparkle/CLI/initialise.py
sparkle/CLI/jobs.py
sparkle/CLI/load_snapshot.py
sparkle/CLI/remove_feature_extractor.py
sparkle/CLI/remove_instances.py
sparkle/CLI/remove_solver.py
sparkle/CLI/run_ablation.py
sparkle/CLI/run_parallel_portfolio.py
sparkle/CLI/run_portfolio_selector.py
sparkle/CLI/run_solvers.py
sparkle/CLI/save_snapshot.py
sparkle/CLI/status.py
sparkle/CLI/wrap.py
sparkle/CLI/help/__init__.py
sparkle/CLI/help/argparse_custom.py
sparkle/CLI/help/global_variables.py
sparkle/CLI/help/jobs.py
sparkle/CLI/help/logging.py
sparkle/CLI/help/nicknames.py
sparkle/CLI/help/snapshot_help.py
sparkle/configurator/__init__.py
sparkle/configurator/configurator.py
sparkle/configurator/configurator_cli.py
sparkle/configurator/implementations/__init__.py
sparkle/configurator/implementations/irace.py
sparkle/configurator/implementations/paramils.py
sparkle/configurator/implementations/smac2.py
sparkle/configurator/implementations/smac3.py
sparkle/configurator/implementations/IRACE/irace_target_algorithm.py
sparkle/configurator/implementations/ParamILS/paramils_target_algorithm.py
sparkle/configurator/implementations/SMAC2/smac2_target_algorithm.py
sparkle/configurator/implementations/SMAC3/smac3_target_algorithm.py
sparkle/instance/__init__.py
sparkle/instance/instances.py
sparkle/platform/__init__.py
sparkle/platform/cli_types.py
sparkle/platform/file_help.py
sparkle/platform/latex.py
sparkle/platform/settings_objects.py
sparkle/platform/output/__init__.py
sparkle/platform/output/configuration_output.py
sparkle/platform/output/parallel_portfolio_output.py
sparkle/platform/output/selection_output.py
sparkle-0.9.6.dist-info/licenses/LICENCE.txt
sparkle-0.9.6.dist-info/METADATA
sparkle-0.9.6.dist-info/WHEEL
sparkle-0.9.6.dist-info/entry_points.txt
sparkle-0.9.6.dist-info/top_level.txt
sparkle-0.9.6.dist-info/RECORD
