Metadata-Version: 2.4
Name: Sparkle
Version: 0.9.6
Summary: Sparkle is a Programming by Optimisation (PbO)-based problem-solving platform designed to enable the widespread and effective use of PbO techniques for improving the state-of-the-art in solving a broad range of prominent AI problems, including SAT and AI Planning. 
Author: Thijs Snelleman, Jeroen Rook, Koen van der Blom, Jeremie Gobeil, Chuan Luo, Holger H. Hoos
Maintainer-email: Thijs Snelleman <snelleman@aim.rwth-aachen.de>, Jeroen Rook <FILL@ME.de>, Hadar Shavit <shavit@aim.rwth-aachen.de>, sparkle@aim.rwth-aachen.de
License-Expression: MIT
Project-URL: Homepage, https://github.com/ADA-research/Sparkle
Project-URL: Documentation, https://ada-research.github.io/Sparkle/
Project-URL: Repository, https://github.com/ADA-research/Sparkle
Project-URL: Issues, https://github.com/ADA-research/Sparkle/issues
Project-URL: Changelog, https://github.com/ADA-research/Sparkle/blob/main/CHANGELOG.md
Keywords: algorithm,configuration,selection,hyperparameter,optimization,empirical,evaluation,solver,sat,ai,planning
Classifier: Programming Language :: Python :: 3.10
Classifier: Programming Language :: Python :: 3.11
Classifier: Programming Language :: Python :: 3.12
Classifier: Programming Language :: Python :: 3.13
Classifier: Natural Language :: English
Classifier: Intended Audience :: Developers
Classifier: Intended Audience :: Education
Classifier: Intended Audience :: Science/Research
Classifier: Operating System :: POSIX :: Linux
Classifier: Operating System :: MacOS
Classifier: Topic :: Scientific/Engineering :: Artificial Intelligence
Classifier: Topic :: Scientific/Engineering
Classifier: Topic :: Software Development
Requires-Python: >=3.10
License-File: LICENCE.txt
Requires-Dist: numpy>=1.26.4
Requires-Dist: pandas==2.3.3
Requires-Dist: filelock==3.19.1
Requires-Dist: smac==2.3.1
Requires-Dist: RunRunner==0.2.0.4
Requires-Dist: asf==0.1.3
Requires-Dist: xgboost==2.1.3
Requires-Dist: scikit-learn==1.3.2
Requires-Dist: plotly==6.1.2
Requires-Dist: kaleido==1.0.0
Requires-Dist: pylatex==1.4.2
Requires-Dist: tabulate==0.9.0
Requires-Dist: pytermgui==7.7.2
Requires-Dist: tqdm==4.66.5
Provides-Extra: dev
Requires-Dist: sparkle[test,tooling]; extra == "dev"
Provides-Extra: tooling
Requires-Dist: ruff==0.12.7; extra == "tooling"
Requires-Dist: pep8-naming==0.13.2; extra == "tooling"
Requires-Dist: pre-commit==3.7.1; extra == "tooling"
Provides-Extra: test
Requires-Dist: pytest==8.1.1; extra == "test"
Requires-Dist: pytest-mock==3.10.0; extra == "test"
Requires-Dist: pytest-cov==5.0.0; extra == "test"
Requires-Dist: pytest-html==4.1.1; extra == "test"
Provides-Extra: docs
Requires-Dist: myst-parser; extra == "docs"
Requires-Dist: Sphinx; extra == "docs"
Requires-Dist: sphinxcontrib-jsmath; extra == "docs"
Requires-Dist: sphinxcontrib-autoprogram; extra == "docs"
Requires-Dist: sphinx-copybutton; extra == "docs"
Requires-Dist: sphinx_rtd_theme==2.0.0; extra == "docs"
Dynamic: license-file
